group44_lab5_part4_processor/alufile.v

module Forwardunit(DATA2,RESULT);
    input signed [7:0] DATA2;
    output wire signed [7:0] RESULT;

    assign #1 RESULT =DATA2;

endmodule

module ADDunit(DATA1,DATA2,RESULT);
    input [7:0] DATA1,DATA2;
    output wire [7:0] RESULT;

    assign #2 RESULT= DATA1+DATA2;
endmodule

module ANDunit(DATA1,DATA2,RESULT);
    input [7:0] DATA1,DATA2;
    output wire [7:0] RESULT;

    assign #1 RESULT = DATA1 & DATA2;
endmodule


module ORunit(DATA1,DATA2,RESULT);
    input [7:0] DATA1,DATA2;
    output wire [7:0] RESULT;

    assign #1 RESULT = DATA1 | DATA2;
endmodule

module MUX4X1(I0,I1,I2,I3,SELECT,RESULT);
    input signed  [7:0] I0,I1,I2,I3;
    input [2:0] SELECT;
    output reg signed [7:0] RESULT;

    always @ (I0,I1,I2,I3,SELECT) begin
        case(SELECT)
            3'b000 : RESULT = I0; //fdout
            3'b001 : RESULT = I1; //addout
            3'b010 : RESULT = I2; //andout
            3'b011 : RESULT = I3; //orout
            //default :RESULT = 8'b00000000;
        endcase
    end
endmodule

module aluunit(DATA1, DATA2, SELECT,RESULT,ZERO);
    input signed [7:0] DATA1,DATA2;
    input [2:0] SELECT;
    output signed [7:0] RESULT;
    output reg ZERO;

    output signed [7:0] fdout,andout,addout,orout;

    Forwardunit FORWARD(DATA2,fdout);
    ADDunit ADD(DATA1,DATA2,addout);
    ANDunit AND(DATA1,DATA2,andout);
    ORunit OR(DATA1,DATA2,orout);
    MUX4X1 MUX(fdout,addout,andout,orout,SELECT,RESULT);

    always @(*) begin
        if ((RESULT == 8'b00000000)) begin
            ZERO = 1'b1;
        end
        else begin
            ZERO = 1'b0;
        end
    end


endmodule

group44_lab5_part4_processor/mux2x1.v
module MUX2X1(input1,input2,select,result);
    input [7:0] input1,input2;
    input select;
    output reg  [7:0] result;

    always @ (input1,input2,select) begin
        if(select)begin
            result = input2;
        end
        else begin
            result =input1;
        end
    end

endmodule

/*always @(I0, I1, sel) begin
    case (sel)
      1'b0: Y = I0;
      1'b1: Y = I1; 
      default: Y = 0;
    endcase
    
  end*/

group44_lab5_part4_processor/twoscomp.v
module twoscomplement(in,out);
    input [7:0] in;
    output reg signed  [7:0] out;
    always @ (in) begin
        #1 out = ~in +1;
    end
endmodule

//or, assign out = ~in + 1;   //remove reg part from out

group44_lab5_part4_processor/regfile.v
module reg_file(IN, OUT1, OUT2, INADDRESS, OUT1ADDRESS, OUT2ADDRESS, WRITE, CLK, RESET);
    input signed [7:0] IN;
    output signed [7:0] OUT1, OUT2;
    input [2:0] INADDRESS, OUT1ADDRESS, OUT2ADDRESS;
    input WRITE, CLK, RESET;

    reg signed [7:0] REGISTER [7:0]; // 8X8 register file
    integer i;

    always @ (posedge CLK ) begin
        if (RESET) begin
            #1
            for (i = 0; i < 8; i = i + 1) begin
                REGISTER[i] = 8'd0;
            end 
        end
        else if (WRITE) begin
            #1 REGISTER[INADDRESS] = IN;
        end
    end

    assign #2 OUT1 = REGISTER[OUT1ADDRESS];
    assign #2 OUT2 = REGISTER[OUT2ADDRESS];
    
endmodule

group44_lab5_part4_processor/controlunit.v
module control_unit(OPCODE,WRITEENABLE,istwocomp,isregout,jump,branch,ALUOP);
    input [7:0] OPCODE;
    output reg WRITEENABLE,istwocomp,isregout;
    output reg [2:0] ALUOP;
    output reg jump,branch;

    /* OP-CODE DEIFINITIONS
	Change these according to op-codes assigned in your processor architecture 
	************************************************************************
	char *op_loadi 	= "00000000";
	char *op_add 	= "00000001";
	char *op_mov 	= "00000010";
	char *op_sub 	= "00000011";
	char *op_and 	= "00000100";
	char *op_or 	= "00000101";
	char *op_j		= "00000110";
	char *op_beq	= "00000111";
	char *op_lwd 	= "00001000";
	char *op_lwi 	= "00001001";
	char *op_swd 	= "00001010";
	char *op_swi 	= "00001011";
	************************************************************************/
	

  always @ (OPCODE) begin
    case(OPCODE)
        //loadi
        8'b00000000: begin
            WRITEENABLE = 1'b1;
            istwocomp = 1'b0;
            isregout = 1'b0; 
            ALUOP = 3'b000;
            jump = 1'b0;
            branch = 1'b0;
        end

        

        //add
        8'b00000001: begin
            
            WRITEENABLE = 1'b1;
            istwocomp = 1'b0;
            isregout = 1'b1; 
            ALUOP = 3'b001;
            jump = 1'b0;
            branch = 1'b0;
        end

        //mov
        8'b00000010: begin
            WRITEENABLE = 1'b1;
            istwocomp = 1'b0;
            isregout = 1'b1; 
            ALUOP = 3'b000;
            jump = 1'b0;
            branch = 1'b0;
        end
        
        //sub
        8'b00000011: begin
            WRITEENABLE = 1'b1;
            istwocomp = 1'b1;
            isregout = 1'b1; 
            ALUOP = 3'b001;
            jump = 1'b0;
            branch = 1'b0;
        end

        //and
        8'b00000100: begin
            WRITEENABLE = 1'b1;
            istwocomp = 1'b0;
            isregout = 1'b1; 
            ALUOP = 3'b010;
            jump = 1'b0;
            branch = 1'b0;
        end

        //or
        8'b00000101: begin
            WRITEENABLE = 1'b1;
            istwocomp = 1'b0;
            isregout = 1'b1; 
            ALUOP = 3'b011;
            jump = 1'b0;
            branch = 1'b0;
        end

        //j
        8'b00000110: begin
            WRITEENABLE = 1'b0;
            istwocomp = 1'b0;
            isregout = 1'b0; 
            ALUOP = 3'b000;
            jump = 1'b1;
            branch = 1'b0;
        end

        //beq
        8'b00000111: begin
            WRITEENABLE = 1'b0;
            istwocomp = 1'b1;
            isregout = 1'b1; 
            ALUOP = 3'b001;
            jump = 1'b0;
            branch = 1'b1;
        end

        /*default: begin
            WRITEENABLE = 1'b0;
            istwocomp = 1'b0;
            isregout = 1'b0; 
            ALUOP = 3'b000;
            jump = 1'b0;
            branch = 1'b0;
        end*/
    endcase
  end
endmodule

group44_lab5_part4_processor/instruction.v
module instructiondecode(INSTRUCTION,OPCODE,IMMEDIATE,READREG1,READREG2,WRITEREG,OFFSET);
    input [31:0] INSTRUCTION;
    output reg [7:0] OPCODE,IMMEDIATE,OFFSET;
    output reg [2:0] READREG1,READREG2,WRITEREG;   
    
    always @ (INSTRUCTION) begin

        OPCODE = INSTRUCTION[31:24];
        IMMEDIATE= INSTRUCTION[7:0];
        READREG1=INSTRUCTION[10:8]; // use 3 bit valu for store reg
        READREG2=INSTRUCTION[2:0];
        WRITEREG=INSTRUCTION[18:16];
        OFFSET = INSTRUCTION[23:16];
    end
endmodule

group44_lab5_part4_processor/mux2x1_32bit.v
module MUX2X1_32BIT(input1,input2,select,result);
    input [31:0] input1,input2;
    input select;
    output reg  [31:0] result;

    always @ (input1,input2,select) begin
        if(select==1'b1)begin
            result = input2;
        end
        else begin
            result =input1;
        end
    end

endmodule

group44_lab5_part4_processor/signandshift.v
module shiftandsign(OFFSET, NOFFSET);
    input [7:0] OFFSET;
    output [31:0] NOFFSET;
    

    
    wire [31:0] extended_offset;
    assign extended_offset = {{24{OFFSET[7]}}, OFFSET};

    // Multiply the extended offset by 4 (equivalent to left-shifting by 2 bits)
    
    assign NOFFSET = extended_offset << 2;

endmodule

group44_lab5_part4_processor/flowcontrol.v
module flowcontrol(jump,branch,ZERO,flowresult);
    input jump,branch,ZERO;
    output reg flowresult;
 
    always @ (*) begin
        flowresult = jump | (branch & ZERO);
    end

endmodule

group44_lab5_part4_processor/pc.v
`include "mux2x1_32bit.v"
`include "flowcontrol.v"
`include "signandshift.v"

module pc_unit(CLK,RESET,PC,jump,branch ,ZERO,OFFSET);
    input CLK,RESET;
    output reg [31:0] PC;
    input jump,branch,ZERO;
    wire flowresult;
    input [7:0] OFFSET;
    wire [31:0] NOFFSET;
    wire [31:0] PC_4,PC_TARGET,PCNEXT;
    
    flowcontrol fcontrol(jump,branch,ZERO,flowresult);
    shiftandsign exbit(OFFSET, NOFFSET);
    assign #1 PC_4 = PC+4;
    assign #2 PC_TARGET = (PC+4) + NOFFSET;

    MUX2X1_32BIT mux32(PC_4,PC_TARGET,flowresult,PCNEXT);


    
    always @(posedge CLK) begin
        if (RESET==1'b1) begin
            #1 PC =0;
        end
        else begin
            #1 PC = PCNEXT;
        end
        
    end
endmodule

group44_lab5_part4_processor/cpu.v

`include "alufile.v"
`include "controlunit.v"
`include "mux2x1.v"
`include "pc.v"
`include "regfile.v"
`include "twoscomp.v"
`include "instruction.v"




module cpu(PC,INSTRUCTION, CLK, RESET);
    input [31:0] INSTRUCTION;
    input CLK,RESET;
    output [31:0] PC;

    

    wire [7:0] OPCODE,IMMEDIATE,OFFSET;
    wire [2:0] READREG1,READREG2,WRITEREG,ALUOP;
    wire WRITEENABLE,isregout,istwocomp;

    wire [7:0] ALURESULT,REGOUT1,REGOUT2,NREGOUT2;
    wire [7:0] m1out,m2out;
    wire branch,jump,ZERO;
    wire [31:0] target;
    wire flowresult;
    wire [31:0] PCCOUNT;

    //decode

    pc_unit mypc(CLK,RESET,PC,jump,branch,ZERO,OFFSET);
    instructiondecode indeco(INSTRUCTION,OPCODE,IMMEDIATE,READREG1,READREG2,WRITEREG,OFFSET);
    control_unit cpucontrol(OPCODE,WRITEENABLE,istwocomp,isregout,jump,branch,ALUOP);//
    reg_file cpuregfile(ALURESULT,REGOUT1,REGOUT2,WRITEREG,READREG1,READREG2, WRITEENABLE, CLK, RESET);//
    twoscomplement cputwoscomp(REGOUT2,NREGOUT2);//
    MUX2X1 mux1(REGOUT2,NREGOUT2,istwocomp,m1out);//
    MUX2X1 mux2(IMMEDIATE,m1out,isregout,m2out);//
    aluunit cpualu(REGOUT1,m2out,ALUOP,ALURESULT,ZERO);//
    
    
endmodule

group44_lab5_part4_processor/cpu_tb.v
`include "cpu.v"

module cpu_tb;

    reg CLK, RESET;
    wire [31:0] PC;
    reg [31:0] INSTRUCTION;
    
    /* 
    ------------------------
     SIMPLE INSTRUCTION MEM
    ------------------------
    */
    
    // Declare an array of registers (8x1024) named 'instr_mem' to be used as instruction memory
    reg [7:0] instr_mem [1023:0]; // Declares an array of 1024 8-bit registers

    // Create combinational logic to support CPU instruction fetching, given the Program Counter(PC) value 
    // (make sure you include the delay for instruction fetching here)
    always @(PC) begin
        // Combining the 8-bit registers into a 32-bit word
        #2 INSTRUCTION = {instr_mem[PC+3], instr_mem[PC+2], instr_mem[PC+1], instr_mem[PC+0]};
    end

    initial begin
        // Initialize instruction memory with the set of instructions you need execute on CPU
        
        // METHOD 1: manually loading instructions to instr_mem
        //{instr_mem[10'd3], instr_mem[10'd2], instr_mem[10'd1], instr_mem[10'd0]} = 32'b00000000000001000000000000000101;
        //{instr_mem[10'd7], instr_mem[10'd6], instr_mem[10'd5], instr_mem[10'd4]} = 32'b00000000000000100000000000001009;
        //{instr_mem[10'd11], instr_mem[10'd10], instr_mem[10'd9], instr_mem[10'd8]} = 32'b00000010000001100000010000000010;
        
        // METHOD 2: loading instr_mem content from instr_mem.mem file
        $readmemb("instr_mem.mem", instr_mem);
        // $readmemb("instr_mem.mem", instr_mem, 0, 10);

    end
    
    /* 
    -----
     CPU
    -----
    */
    cpu mycpu(PC, INSTRUCTION, CLK, RESET);

    initial begin
        CLK = 1'b0;
        RESET = 1'b0;
        
        // Reset the CPU (by giving a pulse to RESET signal) to start the program execution
        #2
        RESET = 1'b1;
        #4
        RESET = 1'b0;

        // finish simulation after some time
        #500
        $finish;
    end
    
    // clock signal generation
    always
        #4 CLK = ~CLK;


    integer i;
    initial begin
        // generate files needed to plot the waveform using GTKWave
        $dumpfile("cpu_wavedata.vcd");
        $dumpvars(0, cpu_tb);

        // To dump the register file values
        for (i = 0; i < 8; i = i + 1) begin
            $dumpvars(1, cpu_tb.mycpu.cpuregfile.REGISTER[i]);
        end
    end
endmodule

group44_lab5_part4_processor/cpu_wavedata.vcd
$date
	Tue Jun 11 21:39:01 2024
$end
$version
	Icarus Verilog
$end
$timescale
	1s
$end
$scope module cpu_tb $end
$var wire 32 ! PC [31:0] $end
$var reg 1 " CLK $end
$var reg 32 # INSTRUCTION [31:0] $end
$var reg 1 $ RESET $end
$var integer 32 % i [31:0] $end
$scope module mycpu $end
$var wire 3 & ALUOP [2:0] $end
$var wire 8 ' ALURESULT [7:0] $end
$var wire 1 ( CLK $end
$var wire 8 ) IMMEDIATE [7:0] $end
$var wire 32 * INSTRUCTION [31:0] $end
$var wire 8 + NREGOUT2 [7:0] $end
$var wire 8 , OFFSET [7:0] $end
$var wire 8 - OPCODE [7:0] $end
$var wire 32 . PC [31:0] $end
$var wire 3 / READREG1 [2:0] $end
$var wire 3 0 READREG2 [2:0] $end
$var wire 8 1 REGOUT1 [7:0] $end
$var wire 8 2 REGOUT2 [7:0] $end
$var wire 1 3 RESET $end
$var wire 1 4 WRITEENABLE $end
$var wire 3 5 WRITEREG [2:0] $end
$var wire 1 6 ZERO $end
$var wire 1 7 branch $end
$var wire 1 8 isregout $end
$var wire 1 9 istwocomp $end
$var wire 1 : jump $end
$var wire 8 ; m1out [7:0] $end
$var wire 8 < m2out [7:0] $end
$scope module mypc $end
$var wire 1 ( CLK $end
$var wire 32 = NOFFSET [31:0] $end
$var wire 8 > OFFSET [7:0] $end
$var wire 32 ? PCNEXT [31:0] $end
$var wire 32 @ PC_4 [31:0] $end
$var wire 32 A PC_TARGET [31:0] $end
$var wire 1 3 RESET $end
$var wire 1 6 ZERO $end
$var wire 1 7 branch $end
$var wire 1 B flowresult $end
$var wire 1 : jump $end
$var reg 32 C PC [31:0] $end
$scope module fcontrol $end
$var wire 1 6 ZERO $end
$var wire 1 7 branch $end
$var wire 1 : jump $end
$var reg 1 D flowresult $end
$upscope $end
$scope module exbit $end
$var wire 32 E NOFFSET [31:0] $end
$var wire 8 F OFFSET [7:0] $end
$var wire 32 G extended_offset [31:0] $end
$upscope $end
$scope module mux32 $end
$var wire 32 H input1 [31:0] $end
$var wire 32 I input2 [31:0] $end
$var wire 1 B select $end
$var reg 32 J result [31:0] $end
$upscope $end
$upscope $end
$scope module indeco $end
$var wire 32 K INSTRUCTION [31:0] $end
$var reg 8 L IMMEDIATE [7:0] $end
$var reg 8 M OFFSET [7:0] $end
$var reg 8 N OPCODE [7:0] $end
$var reg 3 O READREG1 [2:0] $end
$var reg 3 P READREG2 [2:0] $end
$var reg 3 Q WRITEREG [2:0] $end
$upscope $end
$scope module cpucontrol $end
$var wire 8 R OPCODE [7:0] $end
$var reg 3 S ALUOP [2:0] $end
$var reg 1 T WRITEENABLE $end
$var reg 1 U branch $end
$var reg 1 V isregout $end
$var reg 1 W istwocomp $end
$var reg 1 X jump $end
$upscope $end
$scope module cpuregfile $end
$var wire 1 ( CLK $end
$var wire 8 Y IN [7:0] $end
$var wire 3 Z INADDRESS [2:0] $end
$var wire 8 [ OUT1 [7:0] $end
$var wire 3 \ OUT1ADDRESS [2:0] $end
$var wire 8 ] OUT2 [7:0] $end
$var wire 3 ^ OUT2ADDRESS [2:0] $end
$var wire 1 3 RESET $end
$var wire 1 4 WRITE $end
$var integer 32 _ i [31:0] $end
$upscope $end
$scope module cputwoscomp $end
$var wire 8 ` in [7:0] $end
$var reg 8 a out [7:0] $end
$upscope $end
$scope module mux1 $end
$var wire 8 b input1 [7:0] $end
$var wire 8 c input2 [7:0] $end
$var wire 1 9 select $end
$var reg 8 d result [7:0] $end
$upscope $end
$scope module mux2 $end
$var wire 8 e input1 [7:0] $end
$var wire 8 f input2 [7:0] $end
$var wire 1 8 select $end
$var reg 8 g result [7:0] $end
$upscope $end
$scope module cpualu $end
$var wire 8 h DATA1 [7:0] $end
$var wire 8 i DATA2 [7:0] $end
$var wire 8 j RESULT [7:0] $end
$var wire 3 k SELECT [2:0] $end
$var wire 8 l addout [7:0] $end
$var wire 8 m andout [7:0] $end
$var wire 8 n fdout [7:0] $end
$var wire 8 o orout [7:0] $end
$var reg 1 p ZERO $end
$scope module FORWARD $end
$var wire 8 q DATA2 [7:0] $end
$var wire 8 r RESULT [7:0] $end
$upscope $end
$scope module ADD $end
$var wire 8 s DATA1 [7:0] $end
$var wire 8 t DATA2 [7:0] $end
$var wire 8 u RESULT [7:0] $end
$upscope $end
$scope module AND $end
$var wire 8 v DATA1 [7:0] $end
$var wire 8 w DATA2 [7:0] $end
$var wire 8 x RESULT [7:0] $end
$upscope $end
$scope module OR $end
$var wire 8 y DATA1 [7:0] $end
$var wire 8 z DATA2 [7:0] $end
$var wire 8 { RESULT [7:0] $end
$upscope $end
$scope module MUX $end
$var wire 8 | I0 [7:0] $end
$var wire 8 } I1 [7:0] $end
$var wire 8 ~ I2 [7:0] $end
$var wire 8 !" I3 [7:0] $end
$var wire 3 "" SELECT [2:0] $end
$var reg 8 #" RESULT [7:0] $end
$upscope $end
$upscope $end
$upscope $end
$upscope $end
$scope module cpu_tb $end
$scope module mycpu $end
$scope module cpuregfile $end
$var reg 8 $" \REGISTER[0] [7:0] $end
$upscope $end
$upscope $end
$upscope $end
$scope module cpu_tb $end
$scope module mycpu $end
$scope module cpuregfile $end
$var reg 8 %" \REGISTER[1] [7:0] $end
$upscope $end
$upscope $end
$upscope $end
$scope module cpu_tb $end
$scope module mycpu $end
$scope module cpuregfile $end
$var reg 8 &" \REGISTER[2] [7:0] $end
$upscope $end
$upscope $end
$upscope $end
$scope module cpu_tb $end
$scope module mycpu $end
$scope module cpuregfile $end
$var reg 8 '" \REGISTER[3] [7:0] $end
$upscope $end
$upscope $end
$upscope $end
$scope module cpu_tb $end
$scope module mycpu $end
$scope module cpuregfile $end
$var reg 8 (" \REGISTER[4] [7:0] $end
$upscope $end
$upscope $end
$upscope $end
$scope module cpu_tb $end
$scope module mycpu $end
$scope module cpuregfile $end
$var reg 8 )" \REGISTER[5] [7:0] $end
$upscope $end
$upscope $end
$upscope $end
$scope module cpu_tb $end
$scope module mycpu $end
$scope module cpuregfile $end
$var reg 8 *" \REGISTER[6] [7:0] $end
$upscope $end
$upscope $end
$upscope $end
$scope module cpu_tb $end
$scope module mycpu $end
$scope module cpuregfile $end
$var reg 8 +" \REGISTER[7] [7:0] $end
$upscope $end
$upscope $end
$upscope $end
$enddefinitions $end
#0
$dumpvars
bx +"
bx *"
bx )"
bx ("
bx '"
bx &"
bx %"
bx $"
bx #"
bx ""
bx !"
bx ~
bx }
bx |
bx {
bx z
bx y
bx x
bx w
bx v
bx u
bx t
bx s
bx r
bx q
xp
bx o
bx n
bx m
bx l
bx k
bx j
bx i
bx h
bx g
bx f
bx e
bx d
bx c
bx b
bx a
bx `
bx _
bx ^
bx ]
bx \
bx [
bx Z
bx Y
xX
xW
xV
xU
xT
bx S
bx R
bx Q
bx P
bx O
bx N
bx M
bx L
bx K
bx J
bx I
bx H
bx G
bx F
bx00 E
xD
bx C
xB
bx A
bx @
bx ?
bx >
bx00 =
bx <
bx ;
x:
x9
x8
x7
x6
bx 5
x4
03
bx 2
bx 1
bx 0
bx /
bx .
bx -
bx ,
bx +
bx *
bx )
0(
bx '
bx &
b1000 %
0$
bx #
0"
bx !
$end
#2
1$
13
#4
1"
1(
#5
b0 C
b0 !
b0 .
b0 +"
b0 *"
b0 )"
b0 ("
b0 '"
b0 &"
b0 %"
b0 $"
b1000 _
#6
b100 J
b100 ?
b100 @
b100 H
0$
03
#7
0D
0B
b10000 =
b10000 E
b1010 g
b1010 <
b1010 i
b1010 q
b1010 t
b1010 w
b1010 z
0U
07
0X
0:
b0 S
b0 &
b0 k
b0 ""
0V
08
0W
09
1T
14
b100 M
b100 G
b100 ,
b100 >
b100 F
b100 Q
b100 5
b100 Z
b10 P
b10 0
b10 ^
b0 O
b0 /
b0 \
b1010 L
b1010 )
b1010 e
b0 N
b0 -
b0 R
b1000000000000001010 #
b1000000000000001010 *
b1000000000000001010 K
#8
0p
06
b1010 #"
b1010 '
b1010 Y
b1010 j
b0x0x0 m
b0x0x0 x
b0x0x0 ~
bx1x1x o
bx1x1x {
bx1x1x !"
b1010 n
b1010 r
b1010 |
0"
0(
#9
b0 d
b0 ;
b0 f
b10100 A
b10100 I
b0 2
b0 ]
b0 `
b0 b
b0 1
b0 [
b0 h
b0 s
b0 v
b0 y
#10
b0 a
b0 +
b0 c
b0 m
b0 x
b0 ~
b1010 o
b1010 {
b1010 !"
#11
b1010 l
b1010 u
b1010 }
#12
1"
1(
#13
b1010 ("
b100 C
b100 !
b100 .
#14
b1000 J
b1000 ?
b1000 @
b1000 H
#15
b10100 =
b10100 E
b1 g
b1 <
b1 i
b1 q
b1 t
b1 w
b1 z
b101 M
b101 G
b101 ,
b101 >
b101 F
b101 Q
b101 5
b101 Z
b1 P
b1 0
b1 ^
b1 L
b1 )
b1 e
b11000 A
b11000 I
b1010000000000000001 #
b1010000000000000001 *
b1010000000000000001 K
#16
b1 #"
b1 '
b1 Y
b1 j
b1 o
b1 {
b1 !"
b1 n
b1 r
b1 |
0"
0(
#17
b11100 A
b11100 I
b1 l
b1 u
b1 }
#20
1"
1(
#21
b1000 C
b1000 !
b1000 .
b1 )"
#22
b1100 J
b1100 ?
b1100 @
b1100 H
#23
b11000 =
b11000 E
b110 M
b110 G
b110 ,
b110 >
b110 F
b110 Q
b110 5
b110 Z
b100000 A
b100000 I
b1100000000000000001 #
b1100000000000000001 *
b1100000000000000001 K
#24
0"
0(
#25
b100100 A
b100100 I
#28
1"
1(
#29
b1 *"
b1100 C
b1100 !
b1100 .
#30
b10000 J
b10000 ?
b10000 @
b10000 H
#31
b11100 =
b11100 E
b1001 g
b1001 <
b1001 i
b1001 q
b1001 t
b1001 w
b1001 z
b111 M
b111 G
b111 ,
b111 >
b111 F
b111 Q
b111 5
b111 Z
b1001 L
b1001 )
b1001 e
b101000 A
b101000 I
b1110000000000001001 #
b1110000000000001001 *
b1110000000000001001 K
#32
b1001 #"
b1001 '
b1001 Y
b1001 j
b1001 o
b1001 {
b1001 !"
b1001 n
b1001 r
b1001 |
0"
0(
#33
b101100 A
b101100 I
b1001 l
b1001 u
b1001 }
#36
1"
1(
#37
b10000 C
b10000 !
b10000 .
b1001 +"
#38
b10100 J
b10100 ?
b10100 @
b10100 H
#39
b10000 =
b10000 E
b0 g
b0 <
b0 i
b0 q
b0 t
b0 w
b0 z
b1 S
b1 &
b1 k
b1 ""
1V
18
1W
19
b100 M
b100 G
b100 ,
b100 >
b100 F
b100 Q
b100 5
b100 Z
b101 P
b101 0
b101 ^
b100 O
b100 /
b100 \
b101 L
b101 )
b101 e
b11 N
b11 -
b11 R
b110000 A
b110000 I
b11000001000000010000000101 #
b11000001000000010000000101 *
b11000001000000010000000101 K
#40
b0 o
b0 {
b0 !"
b0 n
b0 r
b0 |
0"
0(
#41
1p
16
b0 #"
b0 '
b0 Y
b0 j
b100100 A
b100100 I
b0 l
b0 u
b0 }
b1 2
b1 ]
b1 `
b1 b
b1010 1
b1010 [
b1010 h
b1010 s
b1010 v
b1010 y
#42
b11111111 g
b11111111 <
b11111111 i
b11111111 q
b11111111 t
b11111111 w
b11111111 z
b11111111 d
b11111111 ;
b11111111 f
b11111111 a
b11111111 +
b11111111 c
b1010 o
b1010 {
b1010 !"
#43
b1010 m
b1010 x
b1010 ~
b11111111 o
b11111111 {
b11111111 !"
b11111111 n
b11111111 r
b11111111 |
#44
0p
06
b1001 #"
b1001 '
b1001 Y
b1001 j
b1001 l
b1001 u
b1001 }
1"
1(
#45
b1001 ("
b10100 C
b10100 !
b10100 .
#46
b11000 J
b11000 ?
b11000 @
b11000 H
#47
b100 =
b100 E
1U
17
0T
04
b1 M
b1 G
b1 ,
b1 >
b1 F
b1 Q
b1 5
b1 Z
b110 P
b110 0
b110 ^
b110 L
b110 )
b110 e
b111 N
b111 -
b111 R
b101000 A
b101000 I
b111000000010000010000000110 #
b111000000010000010000000110 *
b111000000010000010000000110 K
b1001 1
b1001 [
b1001 h
b1001 s
b1001 v
b1001 y
#48
b1001 m
b1001 x
b1001 ~
0"
0(
#49
b1000 #"
b1000 '
b1000 Y
b1000 j
b11100 A
b11100 I
b1000 l
b1000 u
b1000 }
#52
1"
1(
#53
b11000 C
b11000 !
b11000 .
#54
b11100 J
b11100 ?
b11100 @
b11100 H
#55
b100000 J
b100000 ?
1D
1B
b11111111 #"
b11111111 '
b11111111 Y
b11111111 j
b1 d
b1 ;
b1 f
b11111111111111111111111111110100 =
b11111111111111111111111111110100 E
b0 g
b0 <
b0 i
b0 q
b0 t
b0 w
b0 z
0U
07
1X
1:
b0 S
b0 &
b0 k
b0 ""
0V
08
0W
09
b11111101 M
b11111111111111111111111111111101 G
b11111101 ,
b11111101 >
b11111101 F
b101 Q
b101 5
b101 Z
b0 P
b0 0
b0 ^
b0 O
b0 /
b0 \
b0 L
b0 )
b0 e
b110 N
b110 -
b110 R
b100000 A
b100000 I
b110111111010000000000000000 #
b110111111010000000000000000 *
b110111111010000000000000000 K
#56
1p
16
b0 #"
b0 '
b0 Y
b0 j
b0 m
b0 x
b0 ~
b1001 o
b1001 {
b1001 !"
b0 n
b0 r
b0 |
0"
0(
#57
b10000 J
b10000 ?
b0 d
b0 ;
b0 f
b10000 A
b10000 I
b1001 l
b1001 u
b1001 }
b0 2
b0 ]
b0 `
b0 b
b0 1
b0 [
b0 h
b0 s
b0 v
b0 y
#58
b0 a
b0 +
b0 c
b0 o
b0 {
b0 !"
#59
b0 l
b0 u
b0 }
#60
1"
1(
#61
b10000 C
b10000 !
b10000 .
#62
b10100 @
b10100 H
#63
0D
0B
b10000 =
b10000 E
0X
0:
b1 S
b1 &
b1 k
b1 ""
1V
18
1W
19
1T
14
b10100 J
b10100 ?
b100 M
b100 G
b100 ,
b100 >
b100 F
b100 Q
b100 5
b100 Z
b101 P
b101 0
b101 ^
b100 O
b100 /
b100 \
b101 L
b101 )
b101 e
b11 N
b11 -
b11 R
b1000 A
b1000 I
b11000001000000010000000101 #
b11000001000000010000000101 *
b11000001000000010000000101 K
#64
0"
0(
#65
b100100 A
b100100 I
b1 2
b1 ]
b1 `
b1 b
b1001 1
b1001 [
b1001 h
b1001 s
b1001 v
b1001 y
#66
b11111111 g
b11111111 <
b11111111 i
b11111111 q
b11111111 t
b11111111 w
b11111111 z
b11111111 d
b11111111 ;
b11111111 f
b11111111 a
b11111111 +
b11111111 c
b1001 o
b1001 {
b1001 !"
#67
b1001 m
b1001 x
b1001 ~
b11111111 o
b11111111 {
b11111111 !"
b11111111 n
b11111111 r
b11111111 |
#68
0p
06
b1000 #"
b1000 '
b1000 Y
b1000 j
b1000 l
b1000 u
b1000 }
1"
1(
#69
b1000 ("
b10100 C
b10100 !
b10100 .
#70
b11000 J
b11000 ?
b11000 @
b11000 H
#71
b100 =
b100 E
1U
17
0T
04
b1 M
b1 G
b1 ,
b1 >
b1 F
b1 Q
b1 5
b1 Z
b110 P
b110 0
b110 ^
b110 L
b110 )
b110 e
b111 N
b111 -
b111 R
b101000 A
b101000 I
b111000000010000010000000110 #
b111000000010000010000000110 *
b111000000010000010000000110 K
b1000 1
b1000 [
b1000 h
b1000 s
b1000 v
b1000 y
#72
b1000 m
b1000 x
b1000 ~
0"
0(
#73
b111 #"
b111 '
b111 Y
b111 j
b11100 A
b11100 I
b111 l
b111 u
b111 }
#76
1"
1(
#77
b11000 C
b11000 !
b11000 .
#78
b11100 J
b11100 ?
b11100 @
b11100 H
#79
b100000 J
b100000 ?
1D
1B
b11111111 #"
b11111111 '
b11111111 Y
b11111111 j
b1 d
b1 ;
b1 f
b11111111111111111111111111110100 =
b11111111111111111111111111110100 E
b0 g
b0 <
b0 i
b0 q
b0 t
b0 w
b0 z
0U
07
1X
1:
b0 S
b0 &
b0 k
b0 ""
0V
08
0W
09
b11111101 M
b11111111111111111111111111111101 G
b11111101 ,
b11111101 >
b11111101 F
b101 Q
b101 5
b101 Z
b0 P
b0 0
b0 ^
b0 O
b0 /
b0 \
b0 L
b0 )
b0 e
b110 N
b110 -
b110 R
b100000 A
b100000 I
b110111111010000000000000000 #
b110111111010000000000000000 *
b110111111010000000000000000 K
#80
1p
16
b0 #"
b0 '
b0 Y
b0 j
b0 m
b0 x
b0 ~
b1000 o
b1000 {
b1000 !"
b0 n
b0 r
b0 |
0"
0(
#81
b10000 J
b10000 ?
b0 d
b0 ;
b0 f
b10000 A
b10000 I
b1000 l
b1000 u
b1000 }
b0 2
b0 ]
b0 `
b0 b
b0 1
b0 [
b0 h
b0 s
b0 v
b0 y
#82
b0 a
b0 +
b0 c
b0 o
b0 {
b0 !"
#83
b0 l
b0 u
b0 }
#84
1"
1(
#85
b10000 C
b10000 !
b10000 .
#86
b10100 @
b10100 H
#87
0D
0B
b10000 =
b10000 E
0X
0:
b1 S
b1 &
b1 k
b1 ""
1V
18
1W
19
1T
14
b10100 J
b10100 ?
b100 M
b100 G
b100 ,
b100 >
b100 F
b100 Q
b100 5
b100 Z
b101 P
b101 0
b101 ^
b100 O
b100 /
b100 \
b101 L
b101 )
b101 e
b11 N
b11 -
b11 R
b1000 A
b1000 I
b11000001000000010000000101 #
b11000001000000010000000101 *
b11000001000000010000000101 K
#88
0"
0(
#89
b100100 A
b100100 I
b1 2
b1 ]
b1 `
b1 b
b1000 1
b1000 [
b1000 h
b1000 s
b1000 v
b1000 y
#90
b11111111 g
b11111111 <
b11111111 i
b11111111 q
b11111111 t
b11111111 w
b11111111 z
b11111111 d
b11111111 ;
b11111111 f
b11111111 a
b11111111 +
b11111111 c
b1000 o
b1000 {
b1000 !"
#91
b1000 m
b1000 x
b1000 ~
b11111111 o
b11111111 {
b11111111 !"
b11111111 n
b11111111 r
b11111111 |
#92
0p
06
b111 #"
b111 '
b111 Y
b111 j
b111 l
b111 u
b111 }
1"
1(
#93
b111 ("
b10100 C
b10100 !
b10100 .
#94
b11000 J
b11000 ?
b11000 @
b11000 H
